Metadata-Version: 2.1
Name: colorcon
Version: 0.1.1
Summary: Colored your text
Home-page: UNKNOWN
Author: Arman Ahmadi
Author-email: armanagha6@gmail.com
Maintainer: Arman Ahmadi
Maintainer-email: armanagha6@gmail.com
License: UNKNOWN
Platform: UNKNOWN
